pygnore/__init__.py
pygnore/api.py
pygnore/exceptions.py
pygnore/gitignore.py
pygnore-0.2.0.dist-info/LICENSE
pygnore-0.2.0.dist-info/METADATA
pygnore-0.2.0.dist-info/WHEEL
pygnore-0.2.0.dist-info/top_level.txt
pygnore-0.2.0.dist-info/RECORD
