Metadata-Version: 2.1
Name: pygnore
Version: 0.2.0
Summary: Client for gitignore.io
Home-page: https://github.com/flipee/pygnore
Author: flipee
Author-email: filipe.nascimento01@fatec.sp.gov.br
License: MIT
Keywords: pygnore gitignore development
Platform: UNKNOWN
Classifier: Development Status :: 3 - Alpha
Classifier: Intended Audience :: Developers
Classifier: Topic :: Software Development
Classifier: License :: OSI Approved :: MIT License
Classifier: Programming Language :: Python :: 3
Requires-Dist: cachetools
Provides-Extra: dev
Requires-Dist: black; extra == 'dev'
Requires-Dist: flake8-bugbear; extra == 'dev'
Requires-Dist: flake8-mypy; extra == 'dev'
Provides-Extra: test
Requires-Dist: coveralls; extra == 'test'
Requires-Dist: flake8; extra == 'test'
Requires-Dist: tox-venv; extra == 'test'
